german_lemmatizer/__init__.py
german_lemmatizer/lemmatize.py
german_lemmatizer-0.1.1.dist-info/LICENSE
german_lemmatizer-0.1.1.dist-info/METADATA
german_lemmatizer-0.1.1.dist-info/WHEEL
german_lemmatizer-0.1.1.dist-info/top_level.txt
german_lemmatizer-0.1.1.dist-info/RECORD
