Metadata-Version: 2.1
Name: german_lemmatizer
Version: 0.1.1
Summary: A Python package (using a Docker image under the hood) to lemmatize German texts.
Home-page: https://github.com/jfilter/german-lemmatizer
Author: Johannes Filter
Author-email: hi@jfilter.de
License: MIT
Platform: UNKNOWN
Classifier: Programming Language :: Python :: 3.6
Classifier: Programming Language :: Python :: 3.7
Classifier: License :: OSI Approved :: MIT License
Classifier: Topic :: Utilities
